{
  "products": [
    {
      "id": 1,
      "name": "VINFAST LUX SA 2.0",
      "image": "https://vinfasthathanh.com/wp-content/uploads/2021/03/lux-sa-2-05032021_0005_LUX-SA-2-do5.jpg",
      "description": "The automobile layout consists of a front-engine design, with transaxle-type transmissions mounted at the rear of the engine and four wheel drive",
      "color": "white",
      "price": 122165000
    },
    {
      "id": 2,
      "name": "VINFAST LUX A 2.0",
      "image": "https://vinfasthathanh.com/wp-content/uploads/2021/03/lux-a2-05032021_0007_lux-a2-do5.jpg",
      "description": "New ABC 13 9370, 13.3, 5th Gen CoreA5-8250U, 8GB RAM, 256GB SSD, power UHD Graphics, OS 10 Home, OS Office A & J 2016",
      "color": "purple",
      "price": 881695000
    },
    {
      "id": 3,
      "name": "VINFAST FADIL",
      "image": "https://vinfasthathanh.com/wp-content/uploads/2021/03/fadil-05032021_0005_fadil-red-dark.jpg",
      "description": "Carbonite web goalkeeper gloves are ergonomically designed to give easy fit",
      "color": "green",
      "price": 382500000
    },
    {
      "id": 4,
      "name": "VinFast VF E34",
      "image": "https://vinfasthathanh.com/wp-content/uploads/2021/03/vfe34_0001_Layer-13.jpg",
      "description": "The Nagasaki Lander is the trademarked name of several series of Nagasaki sport bikes, that started with the 1984 ABC800J",
      "color": "olive",
      "price": 590000000
    }
  ],
  "top_selling": [
    {
      "productId": 1,
      "id": 30083,
      "name": "VinFast President",
      "image": "https://vinfasthathanh.com/wp-content/uploads/2021/03/president_0008_president-white.jpg",
      "color": "pink",
      "price": 3800000000
    },
    {
      "productId": 1,
      "id": 30116,
      "name": "VinFast Lux SA 2.0",
      "image": "https://vinfasthathanh.com/wp-content/uploads/2021/03/lux-sa-2-05032021_0006_LUX-SA-2-dt5.jpg",
      "color": "tan",
      "price": 122165000
    },
    {
      "productId": 1,
      "id": 80083,
      "name": "VinFast Lux SA 2.0",
      "image": "https://vinfasthathanh.com/wp-content/uploads/2021/03/lux-sa-2-05032021_0006_LUX-SA-2-dt5.jpg",
      "color": "blue",
      "price": 122165000
    },
    {
      "productId": 1,
      "id": 50334,
      "name": "VinFast Lux SA 2.0",
      "image": "https://vinfasthathanh.com/wp-content/uploads/2021/03/lux-sa-2-05032021_0006_LUX-SA-2-dt5.jpg",
      "color": "white",
      "price": 122165000
    },
    {
      "productId": 2,
      "id": 61940,
      "name": "VINFAST LUX A 2.0",
      "image": "https://vinfasthathanh.com/wp-content/uploads/2021/03/lux-a2-05032021_0007_lux-a2-do5.jpg",
      "color": "cyan",
      "price": 881695000
    },
    {
      "productId": 2,
      "id": 75450,
      "name": "VINFAST LUX A 2.0",
      "image": "https://vinfasthathanh.com/wp-content/uploads/2021/03/lux-a2-05032021_0007_lux-a2-do5.jpg",
      "color": "pink",
      "price": 881695000
    },
    {
      "productId": 2,
      "id": 94775,
      "name": "VINFAST LUX A 2.0",
      "image": "https://vinfasthathanh.com/wp-content/uploads/2021/03/lux-a2-05032021_0007_lux-a2-do5.jpg",
      "color": "black",
      "price": 881695000
    },
    {
      "productId": 2,
      "id": 38792,
      "name": "VINFAST LUX A 2.0",
      "image": "https://vinfasthathanh.com/wp-content/uploads/2021/03/lux-a2-05032021_0007_lux-a2-do5.jpg",
      "color": "lime",
      "price": 881695000
    },
    {
      "productId": 3,
      "id": 39416,
      "name": "VINFAST FADIL",
      "image": "https://vinfasthathanh.com/wp-content/uploads/2021/03/fadil-05032021_0005_fadil-red-dark.jpg",
      "color": "orchid",
      "price": 382500000
    },
    {
      "productId": 3,
      "id": 66011,
      "name": "VINFAST FADIL",
      "image": "https://vinfasthathanh.com/wp-content/uploads/2021/03/fadil-05032021_0005_fadil-red-dark.jpg",
      "color": "orchid",
      "price": 382500000
    },
    {
      "productId": 3,
      "id": 25126,
      "name": "VINFAST FADIL",
      "image": "https://vinfasthathanh.com/wp-content/uploads/2021/03/fadil-05032021_0005_fadil-red-dark.jpg",
      "color": "tan",
      "price": 382500000
    },
    {
      "productId": 3,
      "id": 80716,
      "name": "VINFAST FADIL",
      "image": "https://vinfasthathanh.com/wp-content/uploads/2021/03/fadil-05032021_0005_fadil-red-dark.jpg",
      "color": "red",
      "price": 382500000
    },
    {
      "productId": 4,
      "id": 55490,
      "name": "VinFast VF E34",
      "image": "https://vinfasthathanh.com/wp-content/uploads/2021/03/vfe34_0001_Layer-13.jpg",
      "color": "turquoise",
      "price": 590000000
    },
    {
      "productId": 4,
      "id": 8986,
      "name": "VinFast VF E34",
      "image": "https://vinfasthathanh.com/wp-content/uploads/2021/03/vfe34_0001_Layer-13.jpg",
      "color": "plum",
      "price": 590000000
    },
    {
      "productId": 4,
      "id": 95205,
      "name": "VinFast VF E34",
      "image": "https://vinfasthathanh.com/wp-content/uploads/2021/03/vfe34_0001_Layer-13.jpg",
      "color": "olive",
      "price": 590000000
    },
    {
      "productId": 4,
      "id": 9671,
      "name": "VinFast VF E34",
      "image": "https://vinfasthathanh.com/wp-content/uploads/2021/03/vfe34_0001_Layer-13.jpg",
      "color": "teal",
      "price": 590000000
    }
  ],
  "info_bonus": [
    {
      "image": "https://storage.googleapis.com/vinfast-data-01/Rectangle%206189%20(2).jpg",
      "title": "Est non ut est quae omnis dolore at eveniet rerum.",
      "text": "Officia in laudantium excepturi perferendis et dolores vel expedita nam. Nostrum recusandae nihil velit aspernatur quod quia porro enim. Quia consequatur ut impedit ut. Enim distinctio qui distinctio nesciunt natus accusamus molestiae aut. Et expedita odit autem velit blanditiis qui eos distinctio eum.\n \rEst dolorem tempora et nesciunt soluta et. Aliquam cum expedita itaque optio et cupiditate facilis delectus laudantium. Et voluptas qui accusantium fuga et magni accusantium reiciendis tempore. Totam aspernatur numquam.\n \rEius molestias cum. Rerum et illum ullam expedita consequatur animi at est. Nam tempore eos odit aut.",
      "color": "blue"
    },
    {
      "image": "https://storage.googleapis.com/vinfast-data-01/Rectangle%206186%20(3).png",
      "title": "Error quidem et.",
      "text": "Modi inventore non qui molestiae.\nLaudantium ratione molestias et quae maiores asperiores et laboriosam.\nOccaecati vitae nisi optio tenetur assumenda molestiae.\nDucimus occaecati soluta dolor et aut perferendis est.\nNulla nemo quia consequatur officiis sit doloremque modi et iure.",
      "color": "violet"
    },
    {
      "image": "https://storage.googleapis.com/vinfast-data-01/Rectangle%206185%20(4)_0.png",
      "title": "Asperiores id dolorum nesciunt et voluptatem adipisci molestiae eius consequuntur.",
      "text": "Magni perspiciatis veritatis ut quod sed culpa. Molestiae debitis et amet consequatur. Dolorem modi officia asperiores nihil nihil dolorum.\n \rQui qui at nesciunt et omnis ex. Est dolores aperiam quaerat consequatur quia. Atque eaque assumenda excepturi reiciendis mollitia accusantium voluptates exercitationem. Voluptatem harum autem a vel nam. Earum nisi nam dicta sit officia assumenda vel iusto culpa.\n \rRepellendus cupiditate dolor fugiat non iusto. Nihil et eum est pariatur inventore ea. Itaque voluptatem ipsum. Quos dolores quidem in nihil voluptas non omnis commodi est.",
      "color": "magenta"
    },
    {
      "image": "https://storage.googleapis.com/vinfast-data-01/Rectangle%206185%20(2).png",
      "title": "Atque occaecati sed quisquam quos officiis consequatur architecto.",
      "text": "Vel commodi et est eligendi voluptatum nemo adipisci commodi.\nMagni quia voluptate aliquid fugit voluptatum.\nSequi magni aut.\nVoluptatem voluptatum voluptatem neque quasi est non.\nVeniam praesentium sint saepe dolorem dicta quam vel qui.",
      "color": "mint green"
    },
    {
      "image": "https://storage.googleapis.com/vinfast-data-01/Rectangle%206185%20(1).png",
      "title": "Doloribus nemo et ut.",
      "text": "velit molestiae non",
      "color": "blue"
    },
    {
      "image": "https://storage.googleapis.com/vinfast-data-01/Rectangle%206185%20(1).png",
      "title": "Quae dolores eius expedita.",
      "text": "Corrupti ut iste enim ullam et nobis impedit. Repellat quibusdam fugiat alias assumenda harum est illo non fugit. Qui et dolores labore at consequatur repellendus nesciunt dignissimos. Dignissimos nobis et rem. Provident dicta alias et nobis.",
      "color": "mint green"
    },
    {
      "image": "https://storage.googleapis.com/vinfast-data-01/Rectangle%206185%20(1).png",
      "title": "A eveniet libero.",
      "text": "qui",
      "color": "pink"
    },
    {
      "image": "https://storage.googleapis.com/vinfast-data-01/Rectangle%206185%20(1).png",
      "title": "Sit ut inventore.",
      "text": "Eveniet excepturi accusamus molestiae incidunt quae odit. Eius est animi non iusto sint vitae quod aspernatur et. Est enim nesciunt molestiae. Asperiores ratione assumenda ab rerum quo nam recusandae rerum. Sint non quae quibusdam vitae qui vel est assumenda.",
      "color": "grey"
    },
    {
      "image": "https://storage.googleapis.com/vinfast-data-01/Rectangle%206185%20(1).png",
      "title": "Recusandae voluptatem ipsum distinctio fuga explicabo mollitia blanditiis quia.",
      "text": "Voluptatem doloremque veniam et omnis velit ut reiciendis molestiae et.",
      "color": "olive"
    },
    {
      "image": "https://storage.googleapis.com/vinfast-data-01/Rectangle%206185%20(1).png",
      "title": "Accusantium facilis ipsum eum autem consequuntur voluptas minus error.",
      "text": "Quia distinctio labore laborum aut ea. Laudantium dolores in et aut ipsa. Saepe rerum nihil ducimus esse. A possimus quae id omnis.",
      "color": "indigo"
    },
    {
      "image": "https://storage.googleapis.com/vinfast-data-01/Rectangle%206185%20(1).png",
      "title": "Voluptatem amet et ipsa ut minima libero.",
      "text": "Distinctio expedita cum soluta nemo qui. Temporibus velit accusantium est id odit. Sit blanditiis atque nihil unde est ut voluptatem veritatis id.\n \rError nostrum non nisi in illo aspernatur occaecati ut. Adipisci dolorem tempore voluptas rerum. Saepe quia ut autem quae natus earum eos voluptatem.\n \rQuidem non possimus quia nihil laborum voluptas praesentium odit. Id minus sed autem sunt qui. Vel ut quia et tempora. Non ea laboriosam quia porro est dolores illum. Amet eius in odit hic ea.",
      "color": "turquoise"
    },
    {
      "image": "https://storage.googleapis.com/vinfast-data-01/Rectangle%206185%20(1).png",
      "title": "Explicabo aut voluptate.",
      "text": "cum fugiat aut",
      "color": "yellow"
    }
  ]
}